flow/__init__.py
flow/layout.py
flow/main.py
flow/Class/nonblocking_input.py
flow/Class/stopWatch.py
flow/modules/burnOutGraph.py
flow/modules/clock.py
flow/modules/deadline.py
flow/modules/toDo.py
flow_tui-0.1.0.dist-info/METADATA
flow_tui-0.1.0.dist-info/WHEEL
flow_tui-0.1.0.dist-info/entry_points.txt
flow_tui-0.1.0.dist-info/top_level.txt
flow_tui-0.1.0.dist-info/RECORD
