Metadata-Version: 2.4
Name: flow-tui
Version: 0.1.0
Summary: Your description here
Requires-Python: >=3.7
Requires-Dist: rich
